[
  {
    "name": "BCG",
    "dueDate": "2025-07-01",
    "maxAge": 1,
    "status": "completed"
  },
  {
    "name": "Hepatitis B (Birth Dose)",
    "dueDate": "2025-07-01",
    "maxAge": 1,
    "status": "completed"
  },
  {
    "name": "OPV-0 (Oral Polio Vaccine)",
    "dueDate": "2025-07-02",
    "maxAge": 1,
    "status": "pending"
  },
  {
    "name": "DTP-1",
    "dueDate": "2025-10-01",
    "maxAge": 6,
    "status": "pending"
  },
  {
    "name": "Hepatitis B-1",
    "dueDate": "2025-10-01",
    "maxAge": 6,
    "status": "pending"
  },
  {
    "name": "Hib-1 (Haemophilus influenzae type b)",
    "dueDate": "2025-10-01",
    "maxAge": 6,
    "status": "pending"
  },
  {
    "name": "Rotavirus-1",
    "dueDate": "2025-10-01",
    "maxAge": 6,
    "status": "pending"
  },
  {
    "name": "PCV-1 (Pneumococcal Conjugate Vaccine)",
    "dueDate": "2025-10-01",
    "maxAge": 6,
    "status": "pending"
  },
  {
    "name": "DTP-2",
    "dueDate": "2025-11-01",
    "maxAge": 7,
    "status": "pending"
  },
  {
    "name": "Measles",
    "dueDate": "2026-07-01",
    "maxAge": 12,
    "status": "pending"
  }
]
